BybitAuthenticator/__init__.py
bybit/__init__.py
bybit-0.2.2.dist-info/METADATA
bybit-0.2.2.dist-info/WHEEL
bybit-0.2.2.dist-info/top_level.txt
bybit-0.2.2.dist-info/RECORD
