Metadata-Version: 2.1
Name: bybit
Version: 0.2.2
Summary: Client for connecting to the Bybit Restful API.
Home-page: https://github.com/bybit-exchange/api-connectors
Author: Simon
Author-email: simon.zhang@bybit.com
License: UNKNOWN
Platform: UNKNOWN
Requires-Dist: urllib3 (==1.24.2)
Requires-Dist: bravado (==10.4.1)
